penaltymodel_maxgap/__init__.py
penaltymodel_maxgap/generation.py
penaltymodel_maxgap/interface.py
penaltymodel_maxgap/package_info.py
penaltymodel_maxgap/smt.py
penaltymodel_maxgap-0.2.0.dist-info/DESCRIPTION.rst
penaltymodel_maxgap-0.2.0.dist-info/METADATA
penaltymodel_maxgap-0.2.0.dist-info/RECORD
penaltymodel_maxgap-0.2.0.dist-info/WHEEL
penaltymodel_maxgap-0.2.0.dist-info/entry_points.txt
penaltymodel_maxgap-0.2.0.dist-info/metadata.json
penaltymodel_maxgap-0.2.0.dist-info/top_level.txt
