Metadata-Version: 2.0
Name: penaltymodel-maxgap
Version: 0.2.0
Summary: Generates penalty models using smt solvers.
Home-page: UNKNOWN
Author: D-Wave Systems Inc.
Author-email: acondello@dwavesys.com
License: Apache 2.0
Platform: UNKNOWN
Requires-Dist: six (<2.0.0,>=1.11.0)
Requires-Dist: dwave-networkx (<0.7.0,>=0.6.0)
Requires-Dist: pysmt (<0.8.0,>=0.7.0)
Requires-Dist: penaltymodel (<0.14.0,>=0.13.0)
Requires-Dist: dimod (<0.7.0,>=0.6.3)
